calculate_statistics/__init__.py
calculate_statistics-1.0.0.dist-info/METADATA
calculate_statistics-1.0.0.dist-info/WHEEL
calculate_statistics-1.0.0.dist-info/top_level.txt
calculate_statistics-1.0.0.dist-info/RECORD
