Metadata-Version: 2.1
Name: calculate_statistics
Version: 1.0.0
Requires-Dist: matplotlib
Requires-Dist: numpy
Requires-Dist: opencv-python
